django_client_emailer/__init__.py
django_client_emailer/sending_mail.py
django_client_emailer-0.9.1.dist-info/LICENSE
django_client_emailer-0.9.1.dist-info/METADATA
django_client_emailer-0.9.1.dist-info/WHEEL
django_client_emailer-0.9.1.dist-info/top_level.txt
django_client_emailer-0.9.1.dist-info/RECORD
