Metadata-Version: 2.1
Name: django-client-emailer
Version: 0.9.1
Summary: A django package which act as a gateway to send email with different clients
Home-page: https://github.com/tardonly/django-client-emailer
Author: tardonly
Author-email: rampratap305@gmail.com
License: UNKNOWN
Platform: UNKNOWN
Classifier: Environment :: Web Environment
Classifier: Framework :: Django
Classifier: Intended Audience :: Developers
Classifier: Operating System :: OS Independent
Classifier: License :: OSI Approved :: MIT License
Classifier: Programming Language :: Python
Classifier: Programming Language :: Python :: 3
Classifier: Programming Language :: Python :: 3.2
Classifier: Programming Language :: Python :: 3.3
Classifier: Topic :: Internet :: WWW/HTTP
Classifier: Topic :: Internet :: WWW/HTTP :: Dynamic Content
Requires-Dist: boto3
Requires-Dist: botocore
Requires-Dist: django
Requires-Dist: mailjet-rest
Requires-Dist: requests
Requires-Dist: validate-email
